screen_master/__init__.py
screen_master/build_screen.py
screen_master/enter_screen.py
screen_master/kill_screen.py
utils/__init__.py
utils/utils.py
screen_master-0.0.2.dist-info/METADATA
screen_master-0.0.2.dist-info/WHEEL
screen_master-0.0.2.dist-info/entry_points.txt
screen_master-0.0.2.dist-info/top_level.txt
screen_master-0.0.2.dist-info/RECORD
