Metadata-Version: 2.1
Name: screen-master
Version: 0.0.2
Summary: A cli tool for interact with GNU screen more easily
Home-page: https://github.com/chienfeng0719/screen-master
Author: Jimmy Yeh
Author-email: chienfeng0719@hotmail.com
License: UNKNOWN
Platform: UNKNOWN
Classifier: Programming Language :: Python :: 3
Classifier: License :: OSI Approved :: MIT License
Classifier: Operating System :: OS Independent
Requires-Python: >=3.6
